golf/__init__.py
golf/middleware.py
golf/auth/__init__.py
golf/auth/api_key.py
golf/auth/factory.py
golf/auth/helpers.py
golf/auth/providers.py
golf/auth/registry.py
golf/cli/__init__.py
golf/cli/branding.py
golf/cli/main.py
golf/commands/__init__.py
golf/commands/build.py
golf/commands/init.py
golf/commands/run.py
golf/core/__init__.py
golf/core/builder.py
golf/core/builder_auth.py
golf/core/builder_metrics.py
golf/core/builder_telemetry.py
golf/core/config.py
golf/core/parser.py
golf/core/telemetry.py
golf/core/transformer.py
golf/examples/__init__.py
golf/examples/basic/.env.example
golf/examples/basic/README.md
golf/examples/basic/auth.py
golf/examples/basic/golf.json
golf/examples/basic/dist/README.md
golf/examples/basic/dist/server.py
golf/examples/basic/dist/components/prompts/welcome.py
golf/examples/basic/dist/components/resources/current_time.py
golf/examples/basic/dist/components/resources/info.py
golf/examples/basic/dist/components/resources/weather/city.py
golf/examples/basic/dist/components/resources/weather/client.py
golf/examples/basic/dist/components/resources/weather/current.py
golf/examples/basic/dist/components/resources/weather/forecast.py
golf/examples/basic/dist/components/tools/calculator.py
golf/examples/basic/dist/components/tools/say/hello.py
golf/examples/basic/dist/golf/auth/__init__.py
golf/examples/basic/dist/golf/auth/api_key.py
golf/examples/basic/dist/golf/auth/factory.py
golf/examples/basic/dist/golf/auth/helpers.py
golf/examples/basic/dist/golf/auth/providers.py
golf/examples/basic/prompts/welcome.py
golf/examples/basic/resources/current_time.py
golf/examples/basic/resources/info.py
golf/examples/basic/resources/weather/city.py
golf/examples/basic/resources/weather/client.py
golf/examples/basic/resources/weather/current.py
golf/examples/basic/resources/weather/forecast.py
golf/examples/basic/tools/calculator.py
golf/examples/basic/tools/say/hello.py
golf/metrics/__init__.py
golf/metrics/collector.py
golf/metrics/registry.py
golf_mcp-0.2.19.dist-info/licenses/LICENSE
golf_mcp-0.2.19.dist-info/METADATA
golf_mcp-0.2.19.dist-info/WHEEL
golf_mcp-0.2.19.dist-info/entry_points.txt
golf_mcp-0.2.19.dist-info/top_level.txt
golf_mcp-0.2.19.dist-info/RECORD
